{
    "credits": [
        {
            "title":"Mentor",
            "body": [
                "Aldia Faulinasari Karma Puteri"
            ]
        },
        {
            "title":"2D Artist",
            "body": [
                "Nandira Nikita Adjani"
            ]
        },
        {
            "title":"3D Artist",
            "body": [
                "Muhammad Fauzi",
                "Togi Martin Panjaitan"
            ]
        },
        {
            "title":"Game Designer",
            "body": [
                "Aurelius Dilectio Yuanata Djatmiko"
            ]
        },
        {
            "title":"Game Producer",
            "body": [
                "Alfian Aldy Hamdani",
                "Kevin Alexander"
            ]
        },
        {
            "title":"Game Programmer",
            "body": [
                "Alfian Aldy Hamdani",
                "Aurelius Dilectio Yuanata Djatmiko"
            ]
        },
        {
            "title":"Game Tester",
            "body": [
                "Aldi Kamaludin"
            ]
        },
        {
            "title":"Product Manager",
            "body": [
                "Kevin Alexander"
            ]
        },
        {
            "title":"Story Writer",
            "body": [
                "Nandira Nikita Adjani"
            ]
        },
        {
            "title":"Support",
            "body": [
                "ANR_Pro (2D Artist)",
                "U Ching (Story Writer)",
                "I Komang Satya Dharma Purusatama",
                "Wildbear (Music)"
            ]
        },
        {
            "title":"Music",
            "body": [
                "Guiding Light by WOW Sound (wowsound.com)",
                "Emotive and Haunting Piano Solo by WOW Sound (wowsound.com)",
                "Sad Emotional Piano by DS Productions"
            ]
        },
        {
            "title":"Sound Effect",
            "body": [
                "acess denied buzz by Jacco18 (freesound.org)",
                "Door, Front, Closing, A.wav by InspectorJ (www.jshaw.co.uk) of Freesound.org",
                "Door, Front, Opening, A.wav by InspectorJ (www.jshaw.co.uk) of Freesound.org",
                "garbage bag plastic throw down apartment staircase and handling.flac by kyles (freesound.org)",
                "Locked Door.wav by MindlessTrails (freesound.org)",
                "opening_small_safe.wav by john721 (freesound.org)",
                "SafeCodeOpen_01.wav by fastson (freesound.org)",
                "Slap (with reverb) by JonasTisell (freesound.org)",
                "Wood Friction 2 by Sheyvan (freesound.org)"
            ]
        }
    ]
}